skyflow/__init__.py
skyflow/audit/__init__.py
skyflow/audit/client.py
skyflow/audit/types/__init__.py
skyflow/audit/types/audit_list_events_request_filter_ops_action_type.py
skyflow/audit/types/audit_list_events_request_filter_ops_context_access_type.py
skyflow/audit/types/audit_list_events_request_filter_ops_context_actor_type.py
skyflow/audit/types/audit_list_events_request_filter_ops_context_auth_mode.py
skyflow/audit/types/audit_list_events_request_filter_ops_resource_type.py
skyflow/audit/types/audit_list_events_request_sort_ops_order_by.py
skyflow/bin_lookup/__init__.py
skyflow/bin_lookup/client.py
skyflow/client.py
skyflow/core/__init__.py
skyflow/core/api_error.py
skyflow/core/client_wrapper.py
skyflow/core/datetime_utils.py
skyflow/core/file.py
skyflow/core/http_client.py
skyflow/core/jsonable_encoder.py
skyflow/core/pagination.py
skyflow/core/pydantic_utilities.py
skyflow/core/query_encoder.py
skyflow/core/remove_none_from_dict.py
skyflow/core/request_options.py
skyflow/core/serialization.py
skyflow/environment.py
skyflow/errors/__init__.py
skyflow/errors/not_found_error.py
skyflow/py.typed
skyflow/records/__init__.py
skyflow/records/client.py
skyflow/types/__init__.py
skyflow/types/audit_event_audit_resource_type.py
skyflow/types/audit_event_context.py
skyflow/types/audit_event_data.py
skyflow/types/audit_event_http_info.py
skyflow/types/batch_record_method.py
skyflow/types/context_access_type.py
skyflow/types/context_auth_mode.py
skyflow/types/detokenize_record_response_value_type.py
skyflow/types/googlerpc_status.py
skyflow/types/protobuf_any.py
skyflow/types/redaction_enum_redaction.py
skyflow/types/request_action_type.py
skyflow/types/v_1_audit_after_options.py
skyflow/types/v_1_audit_event_response.py
skyflow/types/v_1_audit_response.py
skyflow/types/v_1_audit_response_event.py
skyflow/types/v_1_audit_response_event_request.py
skyflow/types/v_1_batch_operation_response.py
skyflow/types/v_1_batch_record.py
skyflow/types/v_1_bin_list_response.py
fern_skyflow-1.0.0.dist-info/METADATA
fern_skyflow-1.0.0.dist-info/WHEEL
fern_skyflow-1.0.0.dist-info/RECORD
